{"Error":false,"Message":null,"JsonData":"{\"Sid\":0,\"Did\":100566,\"Id\":\"160513\",\"Title\":\"拆船業職業災害 高雄市肢體障礙協會理事長張木藤\",\"ImageUrl\":\"https://imedia.culture.tw/iframe/70cd5722e3?api_access_key=1dec6002-a7a0-46bc-ba16-c281b889c092\",\"IndexCode\":\"Culture_Media\",\"CustomColumns\":{\"Description\":\"\\n\\n因為家庭經濟難以支撐，張木藤一家八口陸續從台南鄉下來到高雄投入拆船工作，剛來高雄時全家落腳在獅甲豬圈改建的住處，後來就遷往草衙(大違建)，「都是拆船工搭個木板、棚子住在那裏，有電話或是親友來訪，廟口都會廣播」就這養養活一家八口。\\n\\n退伍後回到拆船工作卻遭鐵板壓傷，導致脊髓受損、腰部以下沒有知覺；「我家八個人，有七個在做拆船工作，五個人在工作過程受傷，其中2個人死亡」張木藤回想拆船場的環境，空氣中天天瀰漫著玻璃棉等各式各樣的粉塵「天空都一閃一閃亮晶晶」，工作現場相當危險，幾乎天天都有人受到輕重傷，跌落、壓傷、撞擊…，不勝枚舉，他的姐姐遭噴飛的鉚釘擊瞎眼睛，父親遭槌頭打傷頭部，哥哥被鐵板壓斃，「有一次船上爆炸，一團血肉模糊就落在我身旁，到現在還忘不了」，「大家都提大仁宮事件，其實大大小小的爆炸、受傷，甚至死亡經常發生」\\n\\n他從受傷的陰霾走出來後，就一直投入在協助脊髓受傷的病友重新走入社會。\\n\\n\",\"Keyword_Rights_2\":\"CC BY\",\"Keyword_Des_Rights_2\":\"CC0\",\"Keyword_Longitude\":\"NULL\",\"Keyword_Latitude\":\"NULL\",\"Original_Url\":\"https://cmsdb.culture.tw/media/A9B03823-F308-42F1-AD24-382D206849F0\",\"Original_Identifier\":\"160513\",\"Keyword_Subject_1\":\"社會與政治 / 產業與經濟\",\"alias\":\"\",\"alternativeHeadline\":\"\",\"Keywords\":\"大仁宮爆炸事件 / 瓦斯工 / 拆船 / 脊髓損傷 / 草衙大違建 / 高雄 / 高雄港 / 傳統產業 / 賽洛瑪颱風\",\"dates\":\"拍攝時間 / 2019/5/13\",\"LastUpdateTime\":\"2019/11/02 14:14:43\",\"Creator\":\"高雄市人民團體聘僱人員職業工會\",\"publisher\":\"\",\"mediaType\":\"影片\",\"language\":\"\",\"timelines\":\"1960-1980\",\"city\":\"高雄市鼓山區\",\"address\":\"高雄市鼓山區河川街76巷6弄8號\",\"lng\":\"\",\"lat\":\"\",\"contributors\":\"\",\"contributor\":\"\",\"size\":\"1280x720，MP4檔\",\"admin\":\"\",\"award\":\"\",\"character\":\"\",\"contentLocation\":\"高雄小港、草衙\",\"acquireWay\":\"\",\"acquireSource\":\"高雄市人民團體聘僱人員職業工會\",\"storage\":\"\",\"version\":\"\",\"isbn\":\"\",\"onlineAuthLink\":\"\",\"stuff\":\"\",\"url\":\"\",\"createOrgName\":\"高雄市政府文化局\",\"citation\":\"高雄市人民團體聘僱人員職業工會\",\"Keyword_Rights_1\":\"\",\"AllImages\":\"https://imedia.culture.tw/iframe/70cd5722e3?api_access_key=1dec6002-a7a0-46bc-ba16-c281b889c092\"}}"}