{"Error":false,"Message":null,"JsonData":"{\"Sid\":0,\"Did\":114916,\"Id\":\"194780\",\"Title\":\"洪圳\",\"ImageUrl\":\"https://dcm.s3.hicloud.net.tw/h_upload/collection/2019-12-18/d3ab6610-2c2d-4893-873f-d261902c3658/洪圳.jpg\",\"IndexCode\":\"Culture_Place\",\"CustomColumns\":{\"Description\":\"紅圳，又稱洪圳。自荷蘭統治時期開始，台灣的土地上就被劃出一條條分隔原漢族群的國境線，其中最知名的就是「土牛紅線」，這是清代臺灣自南而北陸續劃定的幾條國境線。康熙61年(1722)朱一貴事件後，決定以「唯立石禁入番地」隔絕原民和漢人。至乾隆年間變成劃分漢民、「熟番」、「生番」的界限。最初在原民出沒處立石為界，後以山溪為界，無山溪處，一律挑溝堆土，以分界限。界限的土堆，形如臥牛，故稱土牛；所挖掘的深溝，則稱為土牛溝。第一張劃界地圖使用紅線標示番界，因而習稱紅線，以指稱地圖上無形的番界，以土牛代表地形上有形之界限，二者合稱土牛紅線。洪圳是乾隆6年(1741)由知母六與漢人合作開鑿，特徵是寬大深，頗為符合史料記載的「深六尺，闊一丈二尺」。由於台灣人習慣將「溪」稱「圳」，紅圳可能原來是土牛紅線上的一條溪流，被改造成水圳。\",\"Keyword_Rights_2\":\"CC BY\",\"Keyword_Des_Rights_2\":\"CC0\",\"Keyword_Longitude\":\"121.252976\",\"Keyword_Latitude\":\"24.90994\",\"Original_Url\":\"https://cmsdb.culture.tw/place/1C99C489-0D43-4D49-934C-A824B63D58E3\",\"Original_Identifier\":\"194780\",\"Keyword_Subject_1\":\"空間、地域與遷徙\",\"alias\":\"紅圳\",\"alternativeHeadline\":\"\",\"Keywords\":\"八德 / 洪圳 / 紅圳 / 桃園\",\"dates\":\"\",\"LastUpdateTime\":\"2019/12/18 11:28:14\",\"Creator\":\"\",\"publisher\":\"\",\"mediaType\":\"\",\"language\":\"\",\"timelines\":\"日治時期(1895~1948) / 清治時期 / 戰後時期 (1945~)\",\"city\":\"\",\"address\":\"桃園市八德區洪圳\",\"lng\":\"\",\"lat\":\"\",\"contributors\":\"\",\"contributor\":\"\",\"size\":\"\",\"admin\":\"\",\"award\":\"\",\"character\":\"\",\"contentLocation\":\"\",\"acquireWay\":\"\",\"acquireSource\":\"\",\"storage\":\"\",\"version\":\"\",\"isbn\":\"\",\"onlineAuthLink\":\"\",\"stuff\":\"\",\"url\":\"\",\"createOrgName\":\"桃園市政府\",\"citation\":\"\",\"Keyword_Rights_1\":\"\",\"AllImages\":\"https://dcm.s3.hicloud.net.tw/h_upload/collectionOpen/2019-12-18/370afc25-8d1e-4b86-9e72-c0b71d166436/洪圳-O.jpg\"}}"}