{"Sid":0,"Did":114912,"Id":"194776","Title":"茄苳里埤塘公園","ImageUrl":"https://dcm.s3.hicloud.net.tw/h_upload/collection/2019-12-18/ded05642-1dbc-4d84-9a1a-b1c2581181b0/茄苳里埤塘公園.jpg","IndexCode":"Culture_Place","CustomColumns":{"Description":"茄苳埤原名為「鴨仔店埤」，因此地原來是—個販賣鴨子（小鴨）的店舖，因此當地至今仍習稱為鴨仔店，現在被改稱為「茄苳里埤塘」。埤塘公園的水源來自於石門大圳，目前被隔成3口相連的埤塘，在北側的2口較適合遊客憩息。水域環境裡看不到什麼垃圾，是有著優良水域的環境。在埤塘中間的堤防上，設置了涼亭、石椅，兩側柳枝迎風搖擺，縱然在酷暑的正午，仍有微風拂面，頗為愜意。埤岸邊的環湖步道，每天都能夠看到民眾慢走散步。夏日清晨或霞光時間，從此地遠望元智大學校園，可見館樓倒影，波光遴遴，景緻之美，猶如蓬萊仙島。茄苳埤是一個保有相當豐富完整自然環境的優美公園，風景殊美、麗影天設，也是在地居民最好的休閒去處。","Keyword_Rights_2":"CC BY","Keyword_Des_Rights_2":"CC0","Keyword_Longitude":"121.272645","Keyword_Latitude":"24.965564","Original_Url":"https://cmsdb.culture.tw/place/49D704A3-01CF-4ECA-938D-B4A4B0C59BD8","Original_Identifier":"194776","Keyword_Subject_1":"空間、地域與遷徙","alias":"","Keywords":"八德 / 茄苳里埤塘公園 / 桃園","historicalDates":"","LastUpdateTime":"2019/12/18 13:34:37","timelines":"日治時期(1895~1948) / 戰後時期 (1945~)","place":"茄苳里埤塘公園","address":"桃園市八德區茄苳里埤塘公園","longitude":"121.272645","latitude":"24.965564","phone":"","Event":"","relationPeople":"","open":"0","free":"否","openTime":"","openTimeDescription":"","capacity":"","traffic":"","subjection":"臺灣石門農田水利會","tag":"","situation":"","historicalDataBrief":"","historicalData":"","reference":"","writer":"林煒舒","createOrgName":"桃園市政府","source":"","Keyword_Rights_1":"","AllImages":"https://dcm.s3.hicloud.net.tw/h_upload/collectionOpen/2019-12-18/0cba45fb-f09d-4889-93dc-c901cfcf79c8/茄苳里埤塘公園-O.jpg"}}