{"Sid":0,"Did":18035,"Id":"282348","Title":"羅東奠安宮神將－馬元帥","ImageUrl":"https://dcm.s3.hicloud.net.tw/excel/object/2020-02-24/de812ac9-6ecd-4a35-9c08-4dc121482062/collection/5bbed785-bb60-4d62-bb6a-9149b52bb281/108-her-cw-1180-201910261617035db3fc4bc9c870.jpg","IndexCode":"Culture_Object","CustomColumns":{"Description":"\n\n馬元帥（馬靈耀）為北極玄天上帝四大護法元帥之一。馬元帥生有三眼，一目豎立額際，神通廣大，曾降五百火鴉、殺東海龍王，更曾為救母親而大鬧地獄。玉皇大帝封為「華天元帥」 　　羅東奠安宮馬元帥神將可能在日治時期即已出現，可能也有相對應的神明會組織，但尚未有文獻可資應證。可能與溫元帥相同，在戰後因其神明會人數逐漸減少，遂由羅東市場的「肉類小組」奉祀。馬元帥神將平時安置在羅東奠安宮三川殿虎邊，由肉類小組祭拜，三月初三玄天上帝壽誕或該神衹生日時，則會參與廟宇的遶境活動。\n\n","Keyword_Rights_2":"CC BY","Keyword_Des_Rights_2":"CC0","Keyword_Longitude":"121.7692359","Keyword_Latitude":"24.6749781","Original_Url":"https://cmsdb.culture.tw/object/502DFDB4-ABDE-4650-B0C9-77B664492429","Original_Identifier":"282348","Keyword_Subject_1":"民俗與宗教","alias":"","alternativeHeadline":"","Keywords":"肉類小組 / 神將 / 馬元帥 / 奠安宮 / 羅東","dates":"創作時間 / 民國/戰後時期","LastUpdateTime":"2020/02/24 19:52:53","Creator":"不詳","publisher":"","mediaType":"有形文物","language":"","timelines":"","city":"宜蘭縣羅東鎮","address":"中山路三段195號","lng":"121.7692359","lat":"24.6749781","contributors":"","contributor":"賴姿君/ 蔡明志","size":"","admin":"","award":"","character":"","contentLocation":"","acquireWay":"","acquireSource":"","storage":"","version":"","isbn":"","onlineAuthLink":"","stuff":"","url":"","createOrgName":"宜蘭縣政府文化局","citation":"","Keyword_Rights_1":"","AllImages":"https://dcm.s3.hicloud.net.tw/excel/object/2020-02-24/de812ac9-6ecd-4a35-9c08-4dc121482062/collectionOpen/b01c5a9f-7f6f-4f89-83b2-dca689eff569/108-her-cw-1180-re-201910261618365db3fc4bc9c870.jpg"}}