{"Error":false,"Message":null,"JsonData":"{\"Sid\":0,\"Did\":94403,\"Id\":\"282715\",\"Title\":\"蘇澳冷泉季\",\"ImageUrl\":\"https://dcm.s3.hicloud.net.tw/excel/event/2020-02-23/066b8fd4-8d81-471c-a460-edd4dfe1fd66/collection/ea948994-6c79-4934-9019-5f8b25115435/108-sea-en-464-201910281916375db6a44c40a4e0.jpg\",\"IndexCode\":\"Culture_Event\",\"CustomColumns\":{\"Description\":\"\\n\\n蘇澳冷泉是蘇澳鎮的一大特產，這樣珍貴特別的礦泉除了意大利威尼斯擁有以外，東南亞地區僅蘇澳地區擁有，作為全世界唯二的冷泉之一，蘇澳冷泉也被稱為天下第一奇泉。蘇澳冷泉出水區位於蘇澳北方，現蘇澳火車站前約三百公尺處，隨著蘇澳冷泉公園再造工程的竣工啟用，蘇澳鎮公所配合推出蘇澳冷泉季，一系列的消暑活動，也讓蘇澳冷泉季成為宜蘭夏天的一個狂歡嘉年華。 蘇澳冷泉季於七月中開幕，將本地產業、文化、美食資源與公益串聯結合，包括七星嶺登高健行活動、草地音樂藝術節、瘋冷泉打水戰、創意潑水踩街、海風情人節、冷泉路跑賽等各種持續將近一整個月的活動，用冷泉來沁涼遊客與在地居民的炎熱夏天。\\n\\n\",\"Keyword_Rights_2\":\"CC BY\",\"Keyword_Des_Rights_2\":\"CC0\",\"Keyword_Longitude\":\"121.8533264\",\"Keyword_Latitude\":\"24.594229\",\"Original_Url\":\"https://cmsdb.culture.tw/event/0C900A17-5E70-462A-970C-FE6966E4DF47\",\"Original_Identifier\":\"282715\",\"Keyword_Subject_1\":\"藝術與人文\",\"alias\":\"\",\"alternativeHeadline\":\"\",\"Keywords\":\"活動 / 蘇澳 / 蘇澳冷泉\",\"dates\":\"\",\"LastUpdateTime\":\"2020/02/23 23:43:27\",\"Creator\":\"\",\"publisher\":\"\",\"mediaType\":\"\",\"language\":\"\",\"timelines\":\"\",\"city\":\"宜蘭縣\",\"address\":\"不詳\",\"lng\":\"121.8533264\",\"lat\":\"24.594229\",\"contributors\":\"\",\"contributor\":\"莊文生;鄭文嵐;高璇\",\"size\":\"\",\"admin\":\"\",\"award\":\"\",\"character\":\"\",\"contentLocation\":\"\",\"acquireWay\":\"\",\"acquireSource\":\"\",\"storage\":\"\",\"version\":\"\",\"isbn\":\"\",\"onlineAuthLink\":\"\",\"stuff\":\"\",\"url\":\"\",\"createOrgName\":\"宜蘭縣政府文化局\",\"citation\":\"\",\"Keyword_Rights_1\":\"\",\"AllImages\":\"https://dcm.s3.hicloud.net.tw/excel/event/2020-02-23/066b8fd4-8d81-471c-a460-edd4dfe1fd66/collectionOpen/aba7aeb8-53e3-4559-893e-e5b6fd53a2f0/108-sea-en-464-re-201910281917425db6a44c40a4e0.jpg\"}}"}