{"Error":false,"Message":null,"JsonData":"{\"Sid\":0,\"Did\":18173,\"Id\":\"283061\",\"Title\":\"獻給宜蘭城通草紙花藝大師—黃德河先生\",\"ImageUrl\":\"https://dcm.s3.hicloud.net.tw/excel/object/2020-02-24/4f8ccbb5-4342-4021-a3e4-a7b655664b83/collection/e4e95dbc-831a-4c6b-ade2-67dfb1a27b5e/108-cra-cw-624-201912271631215e05bf32363a40.jpg / https://dcm.s3.hicloud.net.tw/excel/object/2020-02-24/4f8ccbb5-4342-4021-a3e4-a7b655664b83/collection/d3f182af-af15-4e24-9a2f-a9ba302e74db/108-cra-cw-624-202001102222365e184325a185c0.gif\",\"IndexCode\":\"Culture_Object\",\"CustomColumns\":{\"Description\":\"\\n\\n〈獻給宜蘭城通草紙花藝大師—黃德河先生〉，作者陳世強，登載在《黃德河的蓪草紙花世界》編者序，於2014年7月出版，主要敘述黃德河先生蓪草花技藝對宜蘭文化資產的貢獻，及黃家家人對於蓪草花工藝資訊的協助與支持，冀望黃德河的技藝傳承能夠繼續生根茁壯。 本文首先記錄由於塑膠花盛行而沉寂二十多年的黃德河藝師，在2007年的一次訪問中被社區及歷史研究者發掘，接著受到縣政府等公部門的重視，重新燃起其生命的另一個春天，使黃德河的蓪草花藝術獲得更多人認識及珍重。文中也提到作者及文史工作者等人不忍其獨門絕活失傳，在社區爭取機會下，於2013年，政府文化單位主辦、鄂王社區承辦的「宜蘭舊城匠師博物館網路暨文化創生計畫舊城工藝傳習營」，在黃家蓪草花店鋪「花玉號」辦理蓪草紙花藝傳習課程，傳授對花藝愛好者關於蓪草花的技藝，希望學員能成為未來推廣的種子，或進一步參與文創產品的開發。文中特別感謝黃家家族的合作與關心，為蓪草花的工藝技術，留下了珍貴紀錄。\\n\\n\",\"Keyword_Rights_2\":\"CC BY / CC BY\",\"Keyword_Des_Rights_2\":\"CC0\",\"Keyword_Longitude\":\"121.745182\",\"Keyword_Latitude\":\"24.7492414\",\"Original_Url\":\"https://cmsdb.culture.tw/object/1817AEE9-9499-481D-9EF0-3EFAC389C365\",\"Original_Identifier\":\"283061\",\"Keyword_Subject_1\":\"民俗與宗教\",\"alias\":\"\",\"alternativeHeadline\":\"\",\"Keywords\":\"花玉號 / 陳世強 / 黃德河 / 蓪草紙花\",\"dates\":\"出版日期 / 2014/07/01\",\"LastUpdateTime\":\"2020/02/24 09:24:36\",\"Creator\":\"陳世強\",\"publisher\":\"宜蘭縣政府文化局\",\"mediaType\":\"圖書及手冊\",\"language\":\"中文\",\"timelines\":\"戰後時期(1945~)\",\"city\":\"宜蘭縣宜蘭市\",\"address\":\"26051 宜蘭縣宜蘭市復興路二段101號\",\"lng\":\"121.745182\",\"lat\":\"24.7492414\",\"contributors\":\"\",\"contributor\":\"陳進傳;林躍龍\",\"size\":\"21×29公分\",\"admin\":\"\",\"award\":\"\",\"character\":\"\",\"contentLocation\":\"宜蘭縣\",\"acquireWay\":\"\",\"acquireSource\":\"\",\"storage\":\"宜蘭縣史館、文化局圖書館\",\"version\":\"\",\"isbn\":\"\",\"onlineAuthLink\":\"\",\"stuff\":\"紙本\",\"url\":\"\",\"createOrgName\":\"宜蘭縣政府文化局\",\"citation\":\"宜蘭縣文化局提供\",\"Keyword_Rights_1\":\"\",\"AllImages\":\"https://dcm.s3.hicloud.net.tw/excel/object/2020-02-24/4f8ccbb5-4342-4021-a3e4-a7b655664b83/collectionOpen/e9345bb9-7e75-4af2-a5af-934e0c2ac313/108-cra-cw-624-re-201912271631555e05bf32363a40.jpg / https://dcm.s3.hicloud.net.tw/excel/object/2020-02-24/4f8ccbb5-4342-4021-a3e4-a7b655664b83/collectionOpen/d5130e1e-5f48-4c62-8664-42a164185e38/108-cra-cw-624-re-202001102223065e184325a185c0.jpg\"}}"}