{"Sid":0,"Did":18279,"Id":"283364","Title":"裱框橘茶花","ImageUrl":"https://dcm.s3.hicloud.net.tw/excel/object/2020-02-24/d3274fe6-9bb8-447d-b78e-85aaaec641c1/collection/7c59a10f-39df-4b49-99b1-7ae91bdf26f7/108-cra-cw-945-201909262102195d8cb69cec6910.jpg","IndexCode":"Culture_Object","CustomColumns":{"Description":"\n\n裱框橘茶花，作者黃德河，材質為蓪草，長：53公分，寬：15公分，高：9公分，為2012年作品。 黃德河先生，又名黃江河，日昭和3年(1928)出生，為宜蘭縣蓪草花傳統工藝師，自幼從8歲起，即開始幫母親黃江查某做蓪草花，其母親的造花技藝源自日本老師。家學淵源外，黃德河尚於27歲時，與台灣人造花藝大師-潘牛教授學習花藝，至此融會貫通，並且創作蓪草花藝，可惜大師於2013年去世。而在過往前一年，黃藝師仍接受邀請，繼續為蓪草花的傳承而努力；該活動為2012年03月31日至7月15日，宜蘭市鄂王社區發展協會與文化局辦理宜蘭舊城百工藝展─「花非花」黃德河的蓪草物語、創意燈籠活動，主要是黃德河配合活動，在自家店鋪「花玉號」辦理蓪草紙花藝傳習課程，傳授蓪草花的技藝，並且為蓪草花的傳承，留下了珍貴紀錄。 裱框的橘茶花，乃活動當時贈送給鄂王社區，留在楊士芳紀念館的作品，橘色茶花幾可亂真，讓人不得不對其精湛之技藝表示由衷讚嘆，實在是值得典藏的工藝藝品。\n\n","Keyword_Rights_2":"CC BY / CC BY","Keyword_Des_Rights_2":"CC0","Keyword_Longitude":"121.7525617","Keyword_Latitude":"24.7589767","Original_Url":"https://cmsdb.culture.tw/object/5B968696-79EB-41A8-8755-7D506E30C437","Original_Identifier":"283364","Keyword_Subject_1":"民俗與宗教","alias":"","alternativeHeadline":"","Keywords":"花玉號 / 黃德河 / 楊士芳紀念館 / 蓪草花 / 橘茶花","dates":"創作時間 / 2012/06/01","LastUpdateTime":"2020/02/24 10:22:02","Creator":"黃德河","publisher":"","mediaType":"照片","language":"中文","timelines":"戰後時期(1945~)","city":"宜蘭縣宜蘭市","address":"宜蘭市城隍街13號","lng":"121.7525617","lat":"24.7589767","contributors":"貢獻者:攝影 / 林思維(工藝童玩組成員)","contributor":"陳進傳;林躍龍","size":"長：53 寬：15 高：9(公分)","admin":"宜蘭市鄂王社區發展協會","award":"","character":"","contentLocation":"宜蘭縣","acquireWay":"","acquireSource":"","storage":"宜蘭市舊城西路66號楊士芳紀念館","version":"","isbn":"","onlineAuthLink":"","stuff":"蓪草花","url":"","createOrgName":"宜蘭縣政府文化局","citation":"本組自行拍攝","Keyword_Rights_1":"","AllImages":"https://dcm.s3.hicloud.net.tw/excel/object/2020-02-24/d3274fe6-9bb8-447d-b78e-85aaaec641c1/collectionOpen/659d7352-f5ae-4eea-bee5-182c320672e8/108-cra-cw-945-re-201909262106585d8cb69cec6910.jpg / https://dcm.s3.hicloud.net.tw/excel/object/2020-02-24/d3274fe6-9bb8-447d-b78e-85aaaec641c1/collectionOpen/0d2c3ad0-34a9-44f9-a218-8724f5ae623a/108-cra-cw-945-re-201912231732315e0082f156f9f0.jpg"}}