{"Error":false,"Message":null,"JsonData":"{\"Sid\":0,\"Did\":18986,\"Id\":\"289069\",\"Title\":\"山花與露珠\",\"ImageUrl\":\"https://dcm.s3.hicloud.net.tw/excel/object/2020-02-24/35647981-f857-44ba-a9bf-e96f5bad7c98/collection/f4d0b639-e06e-45a4-8486-924d3f72f1d1/108-lit-cw-1285-201911021937495dbcfc51bc4050.jpg / https://dcm.s3.hicloud.net.tw/excel/object/2020-02-24/35647981-f857-44ba-a9bf-e96f5bad7c98/collection/f30ecdf2-9959-4764-982c-024dde019bbb/108-lit-cw-1285-201911021937495dbcfc51bc4051.gif\",\"IndexCode\":\"Culture_Object\",\"CustomColumns\":{\"Description\":\"\\n\\n《山花與露珠》是陳良欽的第二本詩集，蒐羅了一些發表過的與未發表過的作品。從這個書名我們就可以發現，陳良欽除了貼近自然外，對生活美有更多的觀察。萬物靜觀皆自得正是他詩作的特色，從生活美學出發，再一步一步窺視他的故鄉宜蘭，書寫他人生的體悟。 此書的文字特色，林煥彰說他「觸覺敏銳，感情細膩，用字凝鍊，語言親切，動詞跳脫，意象突出，文法獨特，形式講究，結構嚴謹」，這樣的形容看似誇張，但我們細讀陳良欽的文字，就會發現一點兒也不為過。他的文字比散文還平易近人，他的意象卻時常峰迴路轉、巧妙轉化，他的形式雜齊並存，營造圖像之感，他的文字偶有宜蘭鄉土語言，有許多觸及宜蘭地景、文化之處，像是〈拜拜〉、〈冬山河出海口的沉思〉、〈澳底遇鷹〉等作品，都是非常值得閱讀的優良詩作。\\n\\n\",\"Keyword_Rights_2\":\"CC BY\",\"Keyword_Des_Rights_2\":\"CC0\",\"Keyword_Longitude\":\"121.745182\",\"Keyword_Latitude\":\"24.7492414\",\"Original_Url\":\"https://cmsdb.culture.tw/object/54E9B822-62A0-4798-B411-C46C14F861EC\",\"Original_Identifier\":\"289069\",\"Keyword_Subject_1\":\"藝術與人文\",\"alias\":\"\",\"alternativeHeadline\":\"蘭陽文學叢書．五十二\",\"Keywords\":\"《山花與露珠》 / 現代詩 / 陳良欽\",\"dates\":\"出版日期 / 2006/05\",\"LastUpdateTime\":\"2020/02/24 14:32:46\",\"Creator\":\"陳良欽\",\"publisher\":\"宜蘭縣政府文化局\",\"mediaType\":\"圖書及手冊\",\"language\":\"中文\",\"timelines\":\"戰後時期(1945~)\",\"city\":\"宜蘭縣宜蘭市\",\"address\":\"復興路二段101號\",\"lng\":\"121.745182\",\"lat\":\"24.7492414\",\"contributors\":\"\",\"contributor\":\"黃憲作;王怡云\",\"size\":\"\",\"admin\":\"\",\"award\":\"\",\"character\":\"\",\"contentLocation\":\"\",\"acquireWay\":\"\",\"acquireSource\":\"\",\"storage\":\"\",\"version\":\"\",\"isbn\":\"986-00-5420-9\",\"onlineAuthLink\":\"\",\"stuff\":\"\",\"url\":\"\",\"createOrgName\":\"宜蘭縣政府文化局\",\"citation\":\"\",\"Keyword_Rights_1\":\"\",\"AllImages\":\"https://dcm.s3.hicloud.net.tw/excel/object/2020-02-24/35647981-f857-44ba-a9bf-e96f5bad7c98/collectionOpen/bc956a2f-8fc7-430c-8835-4df93a7f6c05/108-lit-cw-1285-re-201911131326425dcb870d852b60.jpg\"}}"}