{"Error":false,"Message":null,"JsonData":"{\"Sid\":0,\"Did\":22256,\"Id\":\"302976\",\"Title\":\"曹作清訪談錄\",\"ImageUrl\":\"https://dcm.s3.hicloud.net.tw/collection/2020-01-04/9019e679-7a48-4c80-a04f-883ac9aa3143/p1.9-DSC_0370曹作清.jpg / https://dcm.s3.hicloud.net.tw/collection/2020-01-04/37db14e9-fae2-4cd9-9b09-0e3ee0354a3f/p1.9-DSC_0391曹作清.jpg\",\"IndexCode\":\"Culture_Object\",\"CustomColumns\":{\"Description\":\"\\n\\n曹作清，民國28年3月7日（農曆1月17日）出生，湖南省嘉禾縣扶塘村，民國48年至52年，在政戰學校，留校一年。民國60年至62年，研究所畢業。民國76年退伍。民國95年退休。妻子金湘娟，民國37年12月5日出生，湖南省安鄉縣。\\n\\n曹作清表示來臺時是民國38年，其兄為陸軍訓練指揮部，亦為孫立人鳳山練軍時所成立的指揮部。陸軍訓練司令部在廣州徵兵，當時大哥曹作洵任職陸訓部，官拜上校，在臺督訓軍隊，藉此請鄉親王克武同鄉一趟，要他順便帶家父、我與璋姪三人來臺一遊。想不到這一來竟然造成了兩岸相隔數十年，從此與母親未能見面。曹作清亦擔任軍職，曾帶過蔣孝勇，並長期居住於黃埔新村。\\n\\n\",\"Keyword_Rights_2\":\"CC BY / CC BY\",\"Keyword_Des_Rights_2\":\"CC0\",\"Keyword_Longitude\":\"NULL\",\"Keyword_Latitude\":\"NULL\",\"Original_Url\":\"https://cmsdb.culture.tw/object/1EB27C29-4295-42E6-A31D-62002D724F8B\",\"Original_Identifier\":\"302976\",\"Keyword_Subject_1\":\"社會與政治\",\"alias\":\"\",\"alternativeHeadline\":\"\",\"Keywords\":\"孫立人 / 陸軍訓練指揮部 / 黃埔新村\",\"dates\":\"採訪時間 / 2019/08/19\",\"LastUpdateTime\":\"2020/01/04 16:30:12\",\"Creator\":\"顧超光、熊文華\",\"publisher\":\"\",\"mediaType\":\"其他\",\"language\":\"\",\"timelines\":\"戰後時期 (1945~)\",\"city\":\"\",\"address\":\"\",\"lng\":\"\",\"lat\":\"\",\"contributors\":\"\",\"contributor\":\"顧超光、張岳茹\",\"size\":\"\",\"admin\":\"\",\"award\":\"\",\"character\":\"\",\"contentLocation\":\"\",\"acquireWay\":\"\",\"acquireSource\":\"\",\"storage\":\"\",\"version\":\"\",\"isbn\":\"\",\"onlineAuthLink\":\"\",\"stuff\":\"\",\"url\":\"\",\"createOrgName\":\"高雄市政府文化局\",\"citation\":\"\",\"Keyword_Rights_1\":\"\",\"AllImages\":\"https://dcm.s3.hicloud.net.tw/collectionOpen/2020-01-04/97143de2-5c39-485c-ad08-de09c06ec2a7/p1.9-DSC_0370曹作清.jpg / https://dcm.s3.hicloud.net.tw/collectionOpen/2020-01-04/c7c714e9-33c8-4069-8bd9-5929e29a0125/p1.9-DSC_0391曹作清.jpg\"}}"}