{"Sid":0,"Did":25599,"Id":"312592","Title":"趙健訪談錄","ImageUrl":"https://dcm.s3.hicloud.net.tw/collection/2020-01-02/5be687fe-d41e-4d91-a833-f752b7c51441/趙健.png","IndexCode":"Culture_Object","CustomColumns":{"Description":"\n\n趙健，民國43年出生，我的父親出生於民國四年，畢業於海軍電雷學校，民國36年奉命先來臺灣佈防。因為身為海軍，來臺時間又早，所以杭州老家的家眷就一起來臺灣了。家人先在臺北住了一年，民國37年，搬到左營海軍軍區明德新村29號，直到56年北遷，在左營一共住了19年。因為來的早，所以住進了明德新村最大的一戶眷舍，奶奶、雙親、五個子女，再加上未婚的姑姑叔叔，一大家族均入住明德新村。\n\n趙健早期便住於明德新村，對於該眷村生活描述，有充份的描述，具參考價值。\n\n","Keyword_Rights_2":"CC BY","Keyword_Des_Rights_2":"CC0","Keyword_Longitude":"NULL","Keyword_Latitude":"NULL","Original_Url":"https://cmsdb.culture.tw/object/C2F05D92-3503-4E77-BC70-4122A4A50652","Original_Identifier":"312592","Keyword_Subject_1":"社會與政治","alias":"","alternativeHeadline":"","Keywords":"四海一家 / 左營眷村 / 明德新村 / 趙寧","dates":"創作時間 / 2019/09/24","LastUpdateTime":"2020/01/02 17:56:30","Creator":"周治東","publisher":"","mediaType":"文件","language":"","timelines":"戰後時期 (1945~)","city":"高雄市左營區","address":"","lng":"","lat":"","contributors":"","contributor":"趙健、周治東、陳項華、杜正宇","size":"","admin":"","award":"","character":"","contentLocation":"","acquireWay":"","acquireSource":"","storage":"","version":"","isbn":"","onlineAuthLink":"","stuff":"","url":"","createOrgName":"高雄市政府文化局","citation":"","Keyword_Rights_1":"","AllImages":"https://dcm.s3.hicloud.net.tw/collectionOpen/2020-01-02/f485281e-b580-4794-bf22-3807fdfc788b/趙健.png"}}