{"Sid":0,"Did":45827,"Id":"512816","Title":"利澤簡永安宮木作香爐","ImageUrl":"https://dcm.s3.hicloud.net.tw/excel/object/2020-07-22/a7f849ec-44f0-4cbd-9e50-09196ff6056e/collection/0d9b62e9-5b5e-4e47-a5c6-baca8351edc6/109-her-cw-1525-202007191658455f13fc825eb8f0.jpg","IndexCode":"Culture_Object","CustomColumns":{"Description":"\n\n香爐，又稱「神明爐」，用以在民眾向神焚香祭禱後，可供承載香火的容器。利澤簡永安宮安奉於供桌下桌的香爐，為木作方爐，雙展耳。爐身分上中下三段，上段簡樸無飾，僅兩側以雕有「昭和五年」字樣之錢幣狀構件與香爐雙耳連接。中段往內收束，正面陽刻以「永安宮」三字，三字之間的間隔各雕以花飾；轉角處則雕刻以竹節與竹枝、竹葉。下段量體最大，中央正面採人物戲齣透雕，中央兩位主要人物均執雙鎚，可能是《隋唐演義》中李元霸與裴元慶的對戰；周緣上方陰刻以捐獻者藍阿炉等12人之姓名；兩側陰刻以時間「昭和庚午年」、「孟冬之月」，即1930（昭和5）年冬季時敬獻。香爐雙耳採鳳凰造型，由爐身下段最突出處斜向上展開。\n\n","Keyword_Rights_2":"CC BY","Keyword_Des_Rights_2":"CC0","Keyword_Longitude":"121.8231553","Keyword_Latitude":"24.6666045","Original_Url":"https://cmsdb.culture.tw/object/F27C6954-CFEF-42D9-9961-B23767D37804","Original_Identifier":"512816","Keyword_Subject_1":"民俗與宗教","alias":"","alternativeHeadline":"","Keywords":"昭和 / 神明爐 / 隋唐演義","dates":"創作時間 / 民國民初時期/臺灣的日治時期昭和年間","LastUpdateTime":"2020/10/27 20:04:39","Creator":"不詳","publisher":"","mediaType":"有形文物","language":"","timelines":"","city":"宜蘭縣五結鄉","address":"利澤路26號","lng":"121.8231553","lat":"24.6666045","contributors":"","contributor":"葉永韶／蔡明志","size":"","admin":"","award":"","character":"","contentLocation":"","acquireWay":"","acquireSource":"","storage":"","version":"","isbn":"","onlineAuthLink":"","stuff":"","url":"","createOrgName":"宜蘭縣政府文化局","citation":"燦景古建築研究工作室（2008），《縣定古蹟利澤簡永安宮調查研究》。","Keyword_Rights_1":"","AllImages":"https://dcm.s3.hicloud.net.tw/excel/object/2020-07-22/a7f849ec-44f0-4cbd-9e50-09196ff6056e/collectionOpen/cabfe264-8538-46fa-8c86-d41a40afa107/109-her-cw-1525-re-202007191702245f13fc825eb8f0.jpg"}}