{"Error":false,"Message":null,"JsonData":"{\"Sid\":0,\"Did\":47226,\"Id\":\"514818\",\"Title\":\"在玉里中學圖書館前\",\"ImageUrl\":\"https://dcm.s3.hicloud.net.tw/excel/object/2020-07-24/969e0ea9-a922-4bb9-b1dd-58801a351397/collection/7a9f74ea-f7f5-4fe0-9faf-c996104c7ab9/圖624〈在玉里中學圖書館前〉，約1960 年代.jpg\",\"IndexCode\":\"Culture_Object\",\"CustomColumns\":{\"Description\":\"\\n\\n此張照片為一群學生與老師在玉里中學圖書館前所拍攝之照片。根據其照片上的圖書館旁較小的「民國 四十八年冬」的字樣，再加上現今許多公家機關，甚至是學校內的建築都會在其招牌旁打上落成年代，因此可以判斷1959年（民國48年）可能為此建築之落成的年代。再從其門口之招牌可以清楚地看見，當時此棟建築除了作為圖書館外，亦作為社會教育館。而根據《顧我洄瀾》之作者葉柏強先生所言，後來此建築轉變成了健康中心，而圖書館已經移至他處。此影像收錄於2016年（民國105年）由花蓮文史工作者葉柏強先生撰寫、花蓮縣文化局出版的《顧我洄瀾：花蓮歷史影像集》，書中收錄了大量花蓮在地的歷史影像，如老照片、繪葉書、宣傳摺頁、郵戳樣式等，是深入花蓮文史的重要書籍。\\n\\n\",\"Keyword_Rights_2\":\"CC BY\",\"Keyword_Des_Rights_2\":\"CC0\",\"Keyword_Longitude\":\"NULL\",\"Keyword_Latitude\":\"NULL\",\"Original_Url\":\"https://cmsdb.culture.tw/object/44A09386-6519-4560-B2A4-A6325391E4A4\",\"Original_Identifier\":\"514818\",\"Keyword_Subject_1\":\"空間、地域與遷徙\",\"alias\":\"\",\"alternativeHeadline\":\"\",\"Keywords\":\"玉里 / 葉柏強 / 圖書館 / 顧我洄瀾\",\"dates\":\"拍攝時間 / 民國/戰後時期\",\"LastUpdateTime\":\"2020/12/22 13:45:45\",\"Creator\":\"花蓮縣文化局\",\"publisher\":\"\",\"mediaType\":\"圖書及手冊\",\"language\":\"\",\"timelines\":\"\",\"city\":\"\",\"address\":\"\",\"lng\":\"\",\"lat\":\"\",\"contributors\":\"\",\"contributor\":\"吳緯俊\",\"size\":\"\",\"admin\":\"\",\"award\":\"\",\"character\":\"\",\"contentLocation\":\"\",\"acquireWay\":\"\",\"acquireSource\":\"\",\"storage\":\"\",\"version\":\"\",\"isbn\":\"\",\"onlineAuthLink\":\"\",\"stuff\":\"\",\"url\":\"\",\"createOrgName\":\"花蓮縣文化局\",\"citation\":\"葉柏強，《顧我洄瀾—花蓮歷史影像集》（花蓮縣文化局，2016）\",\"Keyword_Rights_1\":\"\",\"AllImages\":\"https://dcm.s3.hicloud.net.tw/excel/object/2020-07-24/969e0ea9-a922-4bb9-b1dd-58801a351397/collectionOpen/7065a076-d667-456c-9fe6-a78b58bea63f/圖624〈在玉里中學圖書館前〉，約1960 年代.jpg\"}}"}