{"Error":false,"Message":null,"JsonData":"{\"Sid\":0,\"Did\":47797,\"Id\":\"515973\",\"Title\":\"大正四年松尾溫爾寄回故鄉高知的繪葉書1\",\"ImageUrl\":\"https://dcm.s3.hicloud.net.tw/excel/object/2020-07-28/5fd9a079-d69a-49b8-bf6d-7bc122c4d03f/collection/cfe500f3-904d-4935-ad5b-5a47a393121f/圖523〈大正四年松尾溫爾寄回故鄉高知的繪葉書〉，大正4年9月.jpg\",\"IndexCode\":\"Culture_Object\",\"CustomColumns\":{\"Description\":\"\\n\\n此張照片為時任璞石閣支廳長的松尾溫爾先生，於1915年（大正4年）9月寄回家鄉之親筆手寫繪葉書（明信片）。在其上面所蓋之郵戳中，可以清楚地看到其寄出之時間。並且在最右手邊的那一排可以看到松尾溫爾之出身地，那行文字中，清楚地寫到了松尾溫爾先生在日本家鄉之住址──「高知縣香美郡山田町」，即是現日本四國島，高知縣香美市土佐山田町。此張明信片上的收信人為：「松尾助十郎樣」，因此可以判定此為寄給家人為了報平安之明信片。本資料出自於《顧我洄瀾：花蓮歷史影像集》，此書由花蓮出身的葉柏強先生撰寫，是一本擁有大量歷史影像的書籍，於2016年（民國105年）出版，可以透過此書了解花蓮的城市變遷樣貌。\\n\\n\",\"Keyword_Rights_2\":\"CC BY\",\"Keyword_Des_Rights_2\":\"CC0\",\"Keyword_Longitude\":\"NULL\",\"Keyword_Latitude\":\"NULL\",\"Original_Url\":\"https://cmsdb.culture.tw/object/B3520A0B-E634-4399-8A36-E5278A04AE1B\",\"Original_Identifier\":\"515973\",\"Keyword_Subject_1\":\"藝術與人文\",\"alias\":\"\",\"alternativeHeadline\":\"\",\"Keywords\":\"太魯閣 / 玉里 / 松尾溫爾 / 璞石閣 / 繪葉書\",\"dates\":\"拍攝時間 / 1915\",\"LastUpdateTime\":\"2020/12/22 14:36:51\",\"Creator\":\"花蓮縣文化局\",\"publisher\":\"\",\"mediaType\":\"圖書及手冊\",\"language\":\"\",\"timelines\":\"\",\"city\":\"\",\"address\":\"\",\"lng\":\"\",\"lat\":\"\",\"contributors\":\"\",\"contributor\":\"吳緯俊\",\"size\":\"\",\"admin\":\"\",\"award\":\"\",\"character\":\"\",\"contentLocation\":\"\",\"acquireWay\":\"\",\"acquireSource\":\"\",\"storage\":\"\",\"version\":\"\",\"isbn\":\"\",\"onlineAuthLink\":\"\",\"stuff\":\"\",\"url\":\"\",\"createOrgName\":\"花蓮縣文化局\",\"citation\":\"葉柏強，《顧我洄瀾—花蓮歷史影像集》（花蓮縣文化局，2016）\",\"Keyword_Rights_1\":\"\",\"AllImages\":\"https://dcm.s3.hicloud.net.tw/excel/object/2020-07-28/5fd9a079-d69a-49b8-bf6d-7bc122c4d03f/collectionOpen/91e6dcdf-7221-4636-873b-ca865727b2a7/圖523〈大正四年松尾溫爾寄回故鄉高知的繪葉書〉，大正4年9月.jpg\"}}"}