{"Error":false,"Message":null,"JsonData":"{\"Sid\":0,\"Did\":47849,\"Id\":\"516025\",\"Title\":\"花中校門前\",\"ImageUrl\":\"https://dcm.s3.hicloud.net.tw/excel/object/2020-07-28/5fd9a079-d69a-49b8-bf6d-7bc122c4d03f/collection/aac530ad-79d8-4551-bcf9-a7bb806781c6/圖441〈花中校門前〉，約1950 年代.jpg\",\"IndexCode\":\"Culture_Object\",\"CustomColumns\":{\"Description\":\"\\n\\n此為1950年代的花蓮中學校門口，照片中的建築為尚未改建的紅樓，花蓮中學，前身為日治時期的花蓮港廳立花蓮港中學校。1978年（民國67年）校門口經當時第七任的校長葉清元改建為大理石直式的校名牌樓，1984年（民國73年）改建局部的校園圍牆，於周圍興建欄杆，以及於部分牆外種植植物，以作為圍牆之用途。1987年（民國76年）於第九任校長喬兆坤，任內陸續增加圍牆，以致今日花蓮高中四周皆有圍牆、樹叢、欄杆圍繞。1991年（民國80年）紅樓遭拆除，行政單位則移至忠孝樓。此影像收錄於《顧我洄瀾：花蓮歷史影像集》一書，為葉柏強先生撰寫、花蓮縣文化局於2016年（民國105年）出版。書中記錄了花蓮近百年的城市樣貌，是一本擁有豐富文史與圖像資料的書籍。\\n\\n\",\"Keyword_Rights_2\":\"CC BY\",\"Keyword_Des_Rights_2\":\"CC0\",\"Keyword_Longitude\":\"NULL\",\"Keyword_Latitude\":\"NULL\",\"Original_Url\":\"https://cmsdb.culture.tw/object/19E4B952-8C56-4BD6-B31A-F1A2B27E46CB\",\"Original_Identifier\":\"516025\",\"Keyword_Subject_1\":\"空間、地域與遷徙\",\"alias\":\"\",\"alternativeHeadline\":\"\",\"Keywords\":\"正門 / 花蓮中學 / 花蓮高中\",\"dates\":\"拍攝時間 / 民國/戰後時期\",\"LastUpdateTime\":\"2020/12/22 14:58:10\",\"Creator\":\"花蓮縣文化局\",\"publisher\":\"\",\"mediaType\":\"圖書及手冊\",\"language\":\"\",\"timelines\":\"\",\"city\":\"\",\"address\":\"\",\"lng\":\"\",\"lat\":\"\",\"contributors\":\"\",\"contributor\":\"林立欣\",\"size\":\"\",\"admin\":\"\",\"award\":\"\",\"character\":\"\",\"contentLocation\":\"\",\"acquireWay\":\"\",\"acquireSource\":\"\",\"storage\":\"\",\"version\":\"\",\"isbn\":\"\",\"onlineAuthLink\":\"\",\"stuff\":\"\",\"url\":\"\",\"createOrgName\":\"花蓮縣文化局\",\"citation\":\"葉柏強，《顧我洄瀾—花蓮歷史影像集》（花蓮縣文化局，2016）\",\"Keyword_Rights_1\":\"\",\"AllImages\":\"https://dcm.s3.hicloud.net.tw/excel/object/2020-07-28/5fd9a079-d69a-49b8-bf6d-7bc122c4d03f/collectionOpen/68a44b9d-2315-4598-9170-ca03b04335e2/圖441〈花中校門前〉，約1950 年代.jpg\"}}"}