{"Error":false,"Message":null,"JsonData":"{\"Sid\":0,\"Did\":58275,\"Id\":\"601297\",\"Title\":\"古意厝大灶年節菜料理：八寶芋泥\",\"ImageUrl\":\"https://dcm.s3.hicloud.net.tw/collection/2020-11-11/76202d7e-a2cf-4d50-a700-69d6f95c3c86/八寶芋泥 (2).jpg\",\"IndexCode\":\"Culture_Object\",\"CustomColumns\":{\"Description\":\"\\n\\n「八寶」在過去是有錢人家的象徵，代表了「珍貴」與「多」的意思，用在食物上，並無限制一定要放哪八種東西，像紅棗、枸杞、蓮子、龍眼乾、甜豆、葡萄乾等都是常用的食材。在北方較常見的是製成八寶飯；南方人則喜歡把八寶跟在地盛產的芋頭結合，製成甜點。小時候每逢年節拜拜辦桌，這道寓意甚好的八寶芋泥經常會在餐桌上出現。它是一道帶鹹的甜品，作法上是先將芋泥切塊蒸熟，放入碗裡壓成泥狀，拌入豬油、蛋，蒸煮30－40分鐘，倒扣在台灣古早水盤內，淋上已煮好的八寶甜料即可上桌。香軟的芋泥入口即化，混以八寶甜湯食用，香甜很有層次感，是順口好吃的年節好味道。\\n\\n\",\"Keyword_Rights_2\":\"CC BY\",\"Keyword_Des_Rights_2\":\"CC0\",\"Keyword_Longitude\":\"NULL\",\"Keyword_Latitude\":\"NULL\",\"Original_Url\":\"https://cmsdb.culture.tw/object/CFCF3BB3-BADF-4909-A68F-F62FFDD0F8E8\",\"Original_Identifier\":\"601297\",\"Keyword_Subject_1\":\"民俗與宗教\",\"alias\":\"\",\"alternativeHeadline\":\"\",\"Keywords\":\"年節菜 / 宜蘭小吃 / 阿母的手路菜\",\"dates\":\"拍攝時間 / 2020/10/25\",\"LastUpdateTime\":\"2020/12/08 14:00:38\",\"Creator\":\"李日成\",\"publisher\":\"\",\"mediaType\":\"照片\",\"language\":\"\",\"timelines\":\"\",\"city\":\"\",\"address\":\"\",\"lng\":\"\",\"lat\":\"\",\"contributors\":\"\",\"contributor\":\"柯雅薇\",\"size\":\"\",\"admin\":\"\",\"award\":\"\",\"character\":\"\",\"contentLocation\":\"\",\"acquireWay\":\"\",\"acquireSource\":\"\",\"storage\":\"\",\"version\":\"\",\"isbn\":\"\",\"onlineAuthLink\":\"\",\"stuff\":\"\",\"url\":\"\",\"createOrgName\":\"宜蘭縣政府文化局\",\"citation\":\"\",\"Keyword_Rights_1\":\"\",\"AllImages\":\"https://dcm.s3.hicloud.net.tw/collectionOpen/2020-11-11/df5069d1-54eb-4a60-b4bd-b37f398381f9/八寶芋泥 (2).jpg\"}}"}