{"Sid":0,"Did":126690,"Id":"602948","Title":"黑藥仔港","ImageUrl":"https://dcm.s3.hicloud.net.tw/excel/place/2020-11-11/f52184de-33a1-4d5a-8a72-52adcf89a439/collection/e97a843c-945f-4308-9ee9-a1804ec42028/109-sea-pa-2317-202011061638285fa4e6de2e30d0.jpg","IndexCode":"Culture_Place","CustomColumns":{"Description":"\n\n　　「黑藥仔港」指的是萬長春圳四結支圳，其貫穿五結鄉，早期環保意識尚未抬頭，是家庭汙水直接排放主道。加上當時中興紙廠等工業廢水排放，造成圳水汙濁黝黑並發出惡臭，居民乃稱此圳為「黑藥仔港」。\n\n　　「黑藥仔港」的汙水隨著水圳流路，匯入五結排水幹線，沿途流經台興南路、下四北路、國民中路、五結北路、協和北路、孝威路、錦草路、大眾北路直至出海，造成各地水源污染，連累五結排水幹線也被稱為「黑水港」。\n\n　　2001年中興紙廠停業，國民對環保觀念亦日漸成熟，縣府也陸續推動污水下水道系統建設等，今圳道水質已改善甚多。\n\n","Keyword_Rights_2":"CC BY","Keyword_Des_Rights_2":"CC0","Keyword_Longitude":"121.792197","Keyword_Latitude":"24.690454","Original_Url":"https://cmsdb.culture.tw/place/DC0830AC-73B5-4C31-A41D-9179A787F5BD","Original_Identifier":"602948","Keyword_Subject_1":"空間、地域與遷徙","alias":"","Keywords":"中興紙廠 / 四結支圳 / 黑水港 / 萬長春圳","historicalDates":"","LastUpdateTime":"2021/01/05 15:26:43","timelines":"","place":"","address":"宜蘭縣五結鄉五結村","longitude":"121.792197","latitude":"24.690454","phone":"","Event":"","relationPeople":"","open":"0","free":"否","openTime":"","openTimeDescription":"","capacity":"","traffic":"","subjection":"","tag":"","situation":"","historicalDataBrief":"","historicalData":"","reference":"《五結鄉鄉史~探尋舊地名》〈五結鄉公所〉，《宜蘭的自然環境、人文與生態保育》(宜蘭縣環境人文與生態保育學會 呂學麟2014)","writer":"莊文生;鐘碧娟;謝淑娟","createOrgName":"宜蘭縣政府文化局","source":"","Keyword_Rights_1":"","AllImages":"https://dcm.s3.hicloud.net.tw/excel/place/2020-11-11/f52184de-33a1-4d5a-8a72-52adcf89a439/collectionOpen/5d851fd1-8871-4a55-a391-96e87f5002fa/109-sea-pa-2317-re-202011061641495fa4e6de2e30d0.jpg"}}