{"Sid":0,"Did":59000,"Id":"603038","Title":"石花菜的秘密-從海裡到餐桌的遙遠距離(下)","ImageUrl":"https://dcm.s3.hicloud.net.tw/collection/2020-11-12/8e69e735-39e6-446e-90f7-21b7e4c890b7/剛上岸的紫紅色石花菜 (2).jpg","IndexCode":"Culture_Object","CustomColumns":{"Description":"\n\n剛上岸的石花菜如紅寶石般鮮豔飽滿但充滿海藻的腥臭味，此時須趕快剃除躲在裏面的小動物，用淡水浸泡沖洗去除鹽分和雜質然後鋪平曬太陽，傍晚收起來，隔天再次浸泡沖洗（如果直接用大量清水沖洗會導致膠體流失太多降低石花菜品質），攤開檢視雜質、鋪平曬太陽傍晚收起來，如此過程反覆7次才能達到去除腥臭味又保留膠質的效果。這樣細膩的加工過程（各家手法不盡相同）在現代還是無法用機器來取代，所以年輕一輩海邊居民多半不願意傳承這項手藝。就算有年輕人願意做如果沒有經驗豐富的長輩指導，從採摘到晾曬到貯存遵循傳統、顧好細節，是無法做出高品質的石花菜乾，而且還會影響石花菜生態。\n\n","Keyword_Rights_2":"CC BY","Keyword_Des_Rights_2":"CC0","Keyword_Longitude":"NULL","Keyword_Latitude":"NULL","Original_Url":"https://cmsdb.culture.tw/object/1AAB7B8D-A4E0-42C9-B5A3-F0F370BC0FC7","Original_Identifier":"603038","Keyword_Subject_1":"產業與經濟","alias":"","alternativeHeadline":"","Keywords":"浸泡沖洗 / 遵守傳統 / 藻腥味","dates":"拍攝時間 / 2020/09/27","LastUpdateTime":"2020/12/08 15:34:15","Creator":"邱惠菁","publisher":"","mediaType":"有形文物","language":"","timelines":"","city":"","address":"","lng":"","lat":"","contributors":"","contributor":"邱惠菁","size":"","admin":"","award":"","character":"","contentLocation":"","acquireWay":"","acquireSource":"","storage":"","version":"","isbn":"","onlineAuthLink":"","stuff":"","url":"","createOrgName":"宜蘭縣政府文化局","citation":"","Keyword_Rights_1":"","AllImages":"https://dcm.s3.hicloud.net.tw/collectionOpen/2020-11-12/bcf490d5-e5e2-4855-bc05-1f7724db55f4/剛上岸的紫紅色石花菜 (2).jpg"}}