{"Error":false,"Message":null,"JsonData":"{\"Sid\":0,\"Did\":59560,\"Id\":\"604549\",\"Title\":\"利澤簡廣惠宮「澤遍蘭疆」匾\",\"ImageUrl\":\"https://dcm.s3.hicloud.net.tw/excel/object/2020-11-15/e018b493-5349-4eab-904e-b3d0bf0025e5/collection/f01fa074-3746-4cb2-9e8c-80f1457a96b7/109-her-cw-1865-202011141110415faf1736347e70.jpg\",\"IndexCode\":\"Culture_Object\",\"CustomColumns\":{\"Description\":\"\\n\\n　　利澤簡廣惠宮「澤遍蘭疆」匾懸掛在正殿中央神龕上方，為木作橫長形有邊框陽刻金字匾額。匾面因經長年香煙燻黑，無法辨其顏色，但表面仍可見施以螺鈿。\\n\\n　　中行陽刻以「澤遍蘭疆」，意指廣惠尊王德澤遍及整個蘭陽地區。上款為「民國四十一年仲冬」，即1952年，乃是為慶祝廣惠宮重建落成所敬獻。下款為「信士　賴旺枝　葉火□　林宗聘　葉啟宗　葉阿松　林阿松　游礼土　游阿□　林阿水　陳坤目　黃□球　吳金傳　仝謝」，都是利澤簡當地民眾，如林宗聘曾任利澤簡永安宮主任委員。\\n\\n　　「澤遍蘭疆」匾之邊框四邊為捲草紋，四角雕刻以蝴蝶，象徵「賜福」。上方邊框之上再雕飾以雙鳳朝日，邊框左右兩側外各再雕飾以一條龍。\\n\\n\",\"Keyword_Rights_2\":\"CC BY\",\"Keyword_Des_Rights_2\":\"CC0\",\"Keyword_Longitude\":\"121.823904\",\"Keyword_Latitude\":\"24.6670581\",\"Original_Url\":\"https://cmsdb.culture.tw/object/2A0431D5-BA0F-4958-B978-1D6FFA007606\",\"Original_Identifier\":\"604549\",\"Keyword_Subject_1\":\"民俗與宗教\",\"alias\":\"\",\"alternativeHeadline\":\"\",\"Keywords\":\"王公廟 / 林宗聘 / 烏石林家 / 謝安\",\"dates\":\"創作時間 / 民國/戰後時期\",\"LastUpdateTime\":\"2021/01/06 17:48:48\",\"Creator\":\"不詳\",\"publisher\":\"\",\"mediaType\":\"有形文物\",\"language\":\"\",\"timelines\":\"\",\"city\":\"宜蘭縣五結鄉\",\"address\":\"利澤東路7號\",\"lng\":\"121.823904\",\"lat\":\"24.6670581\",\"contributors\":\"\",\"contributor\":\"蔡明志/ 葉永韶\",\"size\":\"\",\"admin\":\"\",\"award\":\"\",\"character\":\"\",\"contentLocation\":\"\",\"acquireWay\":\"\",\"acquireSource\":\"\",\"storage\":\"\",\"version\":\"\",\"isbn\":\"\",\"onlineAuthLink\":\"\",\"stuff\":\"\",\"url\":\"\",\"createOrgName\":\"宜蘭縣政府文化局\",\"citation\":\"\",\"Keyword_Rights_1\":\"\",\"AllImages\":\"https://dcm.s3.hicloud.net.tw/excel/object/2020-11-15/e018b493-5349-4eab-904e-b3d0bf0025e5/collectionOpen/7b883a82-4732-44aa-b223-ea8e3c393653/109-her-cw-1865-re-202011141113105faf1736347e70.jpg\"}}"}